{
  "date": {
    "month": 10,
    "year": 2017
  },
  "incomes": [
    {
      "title": "Sam",
      "plannedAmount": 6000,
      "transactions": [
        {
          "date": "2017-10-03T05:00:00.000Z",
          "description": "1st paycheck",
          "amount": 3000
        }
      ]
    },
    {
      "title": "Ellen",
      "plannedAmount": 600,
      "transactions": [
        {
          "date": "2017-10-04T05:00:00.000Z",
          "description": "1st paycheck",
          "amount": 400
        },
        {
          "date": "2017-10-018T05:00:00.000Z",
          "description": "2nd paycheck",
          "amount": 400
        }
      ]
    },
    {
      "title": "Interest",
      "plannedAmount": 100,
      "transactions": [
        {
          "date": "2017-10-30T05:00:00.000Z",
          "description": "TCU Checking",
          "amount": 25
        },
        {
          "date": "2017-10-31T05:00:00.000Z",
          "description": "House Fund",
          "amount": 20
        },
        {
          "date": "2017-10-19T05:00:00.000Z",
          "description": "Discover Savings",
          "amount": 45
        },
        {
          "date": "2017-10-27T05:00:00.000Z",
          "description": "Baby Fund",
          "amount": 10
        }
      ]
    },
    {
      "title": "Miscellaneous",
      "plannedAmount": 0,
      "transactions": []
    }
  ],
  "expenses": [
    {
      "title": "Investments & Savings",
      "subCategories": [
        {
          "title": "Donations",
          "plannedAmount": 100,
          "transactions": []
        },
        {
          "title": "Roth IRA",
          "plannedAmount": 600,
          "transactions": []
        },
        {
          "title": "Savings",
          "plannedAmount": 0,
          "transactions": []
        }
      ]
    },
    {
      "title": "Apartment",
      "subCategories": [
        {
          "title": "Rent & Water",
          "plannedAmount": 1320,
          "transactions": [
            {
              "date": "2017-10-01T05:00:00.000Z",
              "description": "Rent",
              "amount": 1320
            }
          ]
        },
        {
          "title": "Electric",
          "plannedAmount": 49,
          "transactions": [
            {
              "date": "2017-10-05T05:00:00.000Z",
              "description": "Electric Bill",
              "amount": 49
            }
          ]
        },
        {
          "title": "Internet",
          "plannedAmount": 34,
          "transactions": [
            {
              "date": "2017-10-07T05:00:00.000Z",
              "description": "Internet Bill",
              "amount": 34
            }
          ]
        }
      ]
    },
    {
      "title": "Insurance",
      "subCategories": [
        {
          "title": "Renters'",
          "plannedAmount": 0,
          "transactions": []
        },
        {
          "title": "Life & Disability",
          "plannedAmount": 40,
          "transactions": [
            {
              "date": "2017-10-16T05:00:00.000Z",
              "description": "Premiums",
              "amount": 40
            }
          ]
        },
        {
          "title": "Health",
          "plannedAmount": 365,
          "transactions": []
        },
        {
          "title": "Auto",
          "plannedAmount": 200,
          "transactions": []
        }
      ]
    },
    {
      "title": "Necessities",
      "subCategories": [
        {
          "title": "Transportation",
          "plannedAmount": 200,
          "transactions": [
            {
              "date": "2017-10-10T05:00:00.000Z",
              "description": "Sam gas",
              "amount": 24
            },
            {
              "date": "2017-10-11T05:00:00.000Z",
              "description": "Ellen gas",
              "amount": 20
            }
          ]
        },
        {
          "title": "Groceries",
          "plannedAmount": 226,
          "transactions": [
            {
              "date": "2017-10-01T05:00:00.000Z",
              "description": "1st weekly trip",
              "amount": 38
            },
            {
              "date": "2017-10-08T05:00:00.000Z",
              "description": "2nd weekly trip",
              "amount": 38
            },
            {
              "date": "2017-10-15T05:00:00.000Z",
              "description": "3rd weekly trip",
              "amount": 38
            },
            {
              "date": "2017-10-22T05:00:00.000Z",
              "description": "4th weekly trip",
              "amount": 38
            }
          ]
        },
        {
          "title": "Phone",
          "plannedAmount": 38,
          "transactions": [
            {
              "date": "2017-10-01T05:00:00.000Z",
              "description": "Phone bill",
              "amount": 38
            }
          ]
        },
        {
          "title": "Health Care",
          "plannedAmount": 2046,
          "transactions": []
        },
        {
          "title": "Personal Care",
          "plannedAmount": 24,
          "transactions": [
            {
              "date": "2017-10-09T05:00:00.000Z",
              "description": "Sam haircut",
              "amount": 24
            }
          ]
        },
        {
          "title": "Clothing",
          "plannedAmount": 82,
          "transactions": [
            {
              "date": "2017-10-15T05:00:00.000Z",
              "description": "Target run",
              "amount": 17
            }
          ]
        }
      ]
    },
    {
      "title": "Entertainment",
      "subCategories": [
        {
          "title": "Merchandise",
          "plannedAmount": 22,
          "transactions": []
        },
        {
          "title": "Restaurants & Treats",
          "plannedAmount": 80,
          "transactions": [
            {
              "date": "2017-10-22T05:00:00.000Z",
              "description": "Ben & Jerry's",
              "amount": 7
            }
          ]
        },
        {
          "title": "Gifts",
          "plannedAmount": 50,
          "transactions": [
            {
              "date": "2017-10-02T05:00:00.000Z",
              "description": "Ellen's presents (shh!!)",
              "amount": 57
            }
          ]
        },
        {
          "title": "Recreation",
          "plannedAmount": 0,
          "transactions": []
        }
      ]
    }
  ]
}
